[
    {
        "quest_description": "Catch 10 Pok\u00e9mon",
        "quest_reward": "Trapinch",
        "quest_reward_type": "Pokemon",
        "quest_reward_amount": 1,
        "quest_reward_item_name": "Pokemon",
        "quest_reward_pokemon_name": "Trapinch",
        "quest_reward_pokemon_id": 328,
        "quest_reward_item_id": 0,
        "pokestops": [
            {
                "pokestop_id": "032b9f33369a433bb4c8b0bb3dc0f5b3.16",
                "name": "Globo",
                "latitude": 39.75366,
                "longitude": -8.812859
            },
            {
                "pokestop_id": "098af78ab679495aadb944e4da01fd49.11",
                "name": "Ultramar",
                "latitude": 39.745448,
                "longitude": -8.805844
            },
            {
                "pokestop_id": "0df8fea10368498f97ff03c53648024c.16",
                "name": "Museu S C P",
                "latitude": 39.746818,
                "longitude": -8.812759
            },
            {
                "pokestop_id": "0edd4128468938129017b04e6e9459c2.16",
                "name": "Monumento do parque verde de Leiria",
                "latitude": 39.740157,
                "longitude": -8.821688
            },
            {
                "pokestop_id": "103be0c9e368368ca1cf5cd08c617b70.16",
                "name": "Local de conv\u00edvio e descan\u00e7o",
                "latitude": 39.748322,
                "longitude": -8.931966
            },
            {
                "pokestop_id": "19a9281ab7a83984b81186b81ecf6942.16",
                "name": "Medronheiro",
                "latitude": 39.748255,
                "longitude": -8.801251
            },
            {
                "pokestop_id": "2eb6fcf025c9474d971550339c9512ae.11",
                "name": "Correios Leiria (Post Office)",
                "latitude": 39.743073,
                "longitude": -8.808473
            },
            {
                "pokestop_id": "3c5faebcdd112963b2c435aa37647306",
                "name": "Embaixadores da Comunidade da Niantic",
                "latitude": 39.743543,
                "longitude": -8.806178
            },
            {
                "pokestop_id": "404ac14a7e5040cd83239f0ae35428ea.16",
                "name": "Ponte Pedonal Sul",
                "latitude": 39.748399,
                "longitude": -8.93453
            },
            {
                "pokestop_id": "8185a849d18432d285f930b2131093cf.16",
                "name": "Centro Shotokan Leiria",
                "latitude": 39.747428,
                "longitude": -8.807456
            },
            {
                "pokestop_id": "88049685411c47328f6a0e24fda5894d.16",
                "name": "Anfiteatro",
                "latitude": 39.751453,
                "longitude": -8.809059
            },
            {
                "pokestop_id": "8ed0ec246a4e4238a11b7eef7444c5d4.16",
                "name": "Ponte pedonal sobre a ribeira das bernardas",
                "latitude": 39.744965,
                "longitude": -8.933162
            },
            {
                "pokestop_id": "95d31038518e4c78ab66fdb7b2c5a65f.16",
                "name": "Cal\u00e7ada Portuguesa",
                "latitude": 39.744753,
                "longitude": -8.804849
            },
            {
                "pokestop_id": "a054259cd2763c80b9de8c2c09096fbe.16",
                "name": "Poesia Portuguesa de Janela",
                "latitude": 39.749735,
                "longitude": -8.930832
            },
            {
                "pokestop_id": "a12d18e62f3c4c86981d2a6a4316c9a5.16",
                "name": "Homegame aos Her\u00f3icos Soldados",
                "latitude": 39.746449,
                "longitude": -8.808147
            },
            {
                "pokestop_id": "a175686711784037833ee274d88813d8.16",
                "name": "Galeria Manuel Artur Santos",
                "latitude": 39.742898,
                "longitude": -8.807245
            },
            {
                "pokestop_id": "a49e378787484fcbb18b5e98c10bc755.16",
                "name": "Igreja Man\u00e1",
                "latitude": 39.741498,
                "longitude": -8.799315
            },
            {
                "pokestop_id": "a55789a0b055357b8f42ccdc0907d810.16",
                "name": "Parque Infantil Este",
                "latitude": 39.735664,
                "longitude": -8.800658
            },
            {
                "pokestop_id": "b864b45f668840c3b43e2e2fb3dddc11.16",
                "name": "Edif\u00edcio Da Resinagem",
                "latitude": 39.749198,
                "longitude": -8.932709
            },
            {
                "pokestop_id": "bec2eb07d3e344378617c29ab4eff35a.16",
                "name": "Esta\u00e7\u00e3o de Treino - Jardim da Vala Real",
                "latitude": 39.74317,
                "longitude": -8.804189
            },
            {
                "pokestop_id": "c5e96e69dbd13b3eab5f62d3ff424bec.16",
                "name": "Gin\u00e1sio Fit On Move",
                "latitude": 39.745658,
                "longitude": -8.803177
            },
            {
                "pokestop_id": "cf5128f668ae4319ad40b95b5048b22e.16",
                "name": "As Cisternas do Castelo",
                "latitude": 39.747505,
                "longitude": -8.809466
            },
            {
                "pokestop_id": "d4c892ef2a9830bcb1e3eb1541a35a8a.16",
                "name": "Marinha Grande",
                "latitude": 39.747761,
                "longitude": -8.936047
            },
            {
                "pokestop_id": "f20cf939cb55424184465327db0ec8e8.16",
                "name": "Playcity 006",
                "latitude": 39.746676,
                "longitude": -8.802645
            },
            {
                "pokestop_id": "f5a72fe1b79349dcae11646b2d0de99a.11",
                "name": "Mercado de Sant'ana",
                "latitude": 39.74304,
                "longitude": -8.807411
            }
        ]
    },
    {
        "quest_description": "Catch 10 Pok\u00e9mon",
        "quest_reward": "Swablu",
        "quest_reward_type": "Pokemon",
        "quest_reward_amount": 1,
        "quest_reward_item_name": "Pokemon",
        "quest_reward_pokemon_name": "Swablu",
        "quest_reward_pokemon_id": 333,
        "quest_reward_item_id": 0,
        "pokestops": [
            {
                "pokestop_id": "05e2a30a3d5e4fc1824752abcc7a4f69.16",
                "name": "Graffiti Matilha",
                "latitude": 39.742945,
                "longitude": -8.803099
            },
            {
                "pokestop_id": "0b5569737a8438f0abfdf718370b73eb.16",
                "name": "Amieiro",
                "latitude": 39.733619,
                "longitude": -8.797415
            },
            {
                "pokestop_id": "245ac00e7b663a53a8d4073edfab124b.16",
                "name": "Circuito Manuten\u00e7\u00e3o - Patins",
                "latitude": 39.738722,
                "longitude": -8.821751
            },
            {
                "pokestop_id": "29861b24bf8b3ee49c80d19319c2c0ad.16",
                "name": "Catalpa",
                "latitude": 39.745748,
                "longitude": -8.804397
            },
            {
                "pokestop_id": "2bb365fb0c844f4fb27f8ff3e15e9e60.11",
                "name": "Seu Nome Era Mural",
                "latitude": 39.746244,
                "longitude": -8.807457
            },
            {
                "pokestop_id": "300f8d0be9d2491ab4c578c377120e03.16",
                "name": "Marco de Correio",
                "latitude": 39.734008,
                "longitude": -8.808168
            },
            {
                "pokestop_id": "3014a8690b2b49ba8918cad211918966.16",
                "name": "Mural De Namorados",
                "latitude": 39.743299,
                "longitude": -8.803428
            },
            {
                "pokestop_id": "364a7a745fb547b5914ce2b76a8e8ddc.16",
                "name": "Parque De Merendas - Campus 2",
                "latitude": 39.735284,
                "longitude": -8.821824
            },
            {
                "pokestop_id": "3a4298de80593eb885910e275b595736.16",
                "name": "Gin\u00e1sio Luis Lopes",
                "latitude": 39.743959,
                "longitude": -8.798023
            },
            {
                "pokestop_id": "475f3b383bfc30939d994b3a26749c18.16",
                "name": "Edif\u00edcio Comendador",
                "latitude": 39.742053,
                "longitude": -8.809737
            },
            {
                "pokestop_id": "4aa5e2170a2c44e09a15d67b534da5f7.16",
                "name": "Audit\u00f3rio",
                "latitude": 39.749766,
                "longitude": -8.926395
            },
            {
                "pokestop_id": "5f50be390dfb4f50b66319b20cb6cc55.16",
                "name": "Marco CTT",
                "latitude": 39.747797,
                "longitude": -8.803171
            },
            {
                "pokestop_id": "61f76786db87485e8eef8f2e1d2968f1.16",
                "name": "A Juventude a Ci\u00eancia e o Mar",
                "latitude": 39.743887,
                "longitude": -8.805803
            },
            {
                "pokestop_id": "692fb081edc349979975cb8a4a8d5af5.16",
                "name": "Parque Do Museu Do Vidro",
                "latitude": 39.74908,
                "longitude": -8.933678
            },
            {
                "pokestop_id": "6fe0da2a1e864d2780bafd92935a8008.16",
                "name": "Escultura Edifoz",
                "latitude": 39.746497,
                "longitude": -8.815913
            },
            {
                "pokestop_id": "75267162613a4677b0e8895c929e2c52.16",
                "name": "Igreja Batista da Lagoinha",
                "latitude": 39.740459,
                "longitude": -8.80699
            },
            {
                "pokestop_id": "782815cfe6ea4d30b6f63bb601c6360c.16",
                "name": "Tribunal Da Marinha Grande",
                "latitude": 39.753741,
                "longitude": -8.932369
            },
            {
                "pokestop_id": "88201671521f45388828ef0e2d2d3f8a.16",
                "name": "Clube dos ca\u00e7adores",
                "latitude": 39.751363,
                "longitude": -8.937626
            },
            {
                "pokestop_id": "88cdcb6d570d4c1bbad94a55d966d4c5.16",
                "name": "Anfiteatro Praceta Abra\u00e3o Zacuto",
                "latitude": 39.749235,
                "longitude": -8.802702
            },
            {
                "pokestop_id": "89dbb0af65bb450bb804eee0d872e639.16",
                "name": "Ponte pedonal sobre a Ribeira das Bernardas.",
                "latitude": 39.740265,
                "longitude": -8.929824
            },
            {
                "pokestop_id": "8be5956c59cc3621a677fff8c99d12c6.16",
                "name": "Associa\u00e7\u00e3o de Dan\u00e7a de Leiria",
                "latitude": 39.749055,
                "longitude": -8.811604
            },
            {
                "pokestop_id": "8f7b6c291e7d40b7bdd98801018beff9.16",
                "name": "Farol",
                "latitude": 39.750152,
                "longitude": -8.931811
            },
            {
                "pokestop_id": "91b8d3f18fb64e31a31996aec26f6ac8.16",
                "name": "Ponte Euro 2004",
                "latitude": 39.752764,
                "longitude": -8.814174
            },
            {
                "pokestop_id": "b24ea2a380af4589ae3f613b3dfe1e7c.16",
                "name": "Edif\u00edcio \"O Pa\u00e7o\"",
                "latitude": 39.745253,
                "longitude": -8.80654
            },
            {
                "pokestop_id": "d47848cf08e945c691b195b0df815135.16",
                "name": "Artes Manuais",
                "latitude": 39.742853,
                "longitude": -8.933931
            },
            {
                "pokestop_id": "d74ad1450c324939b4b68f6a7c9cb024.16",
                "name": "Homenagem a Dr. An\u00edbal Couceiro",
                "latitude": 39.750433,
                "longitude": -8.932692
            },
            {
                "pokestop_id": "dd49753770a13bbc853fec6b29c52e72.16",
                "name": "Sede de Imprensa Marinha Grande",
                "latitude": 39.753915,
                "longitude": -8.932095
            },
            {
                "pokestop_id": "de7d0cc92e0e4b62b195f7a846d06f79.16",
                "name": "Urban Fitness",
                "latitude": 39.748953,
                "longitude": -8.802133
            },
            {
                "pokestop_id": "f99206298061310da2599051b487f4ef.16",
                "name": "Parque Infantil",
                "latitude": 39.731552,
                "longitude": -8.809623
            },
            {
                "pokestop_id": "ffa50f037c35420faa2db4536ac3bc3e.11",
                "name": "Est\u00e1tua Vacas",
                "latitude": 39.745118,
                "longitude": -8.804209
            }
        ]
    },
    {
        "quest_description": "Catch 10 Fire-type Pok\u00e9mon",
        "quest_reward": "2 Pinap Berry",
        "quest_reward_type": "Item",
        "quest_reward_amount": 2,
        "quest_reward_item_name": "Pinap Berry",
        "quest_reward_pokemon_name": "",
        "quest_reward_pokemon_id": "000",
        "quest_reward_item_id": 705,
        "pokestops": [
            {
                "pokestop_id": "0a24790da0af39809c89230721e5ace9.16",
                "name": "Terra\u00e7o do Ateneu",
                "latitude": 39.739192,
                "longitude": -8.818713
            },
            {
                "pokestop_id": "6d59dc9c55f743179a8cb5f6fb59a86f.16",
                "name": "Placa Informativa - Antes do Castelo",
                "latitude": 39.747749,
                "longitude": -8.808107
            }
        ]
    },
    {
        "quest_description": "Use 5 Berries to help catch Pok\u00e9mon",
        "quest_reward": "Surskit",
        "quest_reward_type": "Pokemon",
        "quest_reward_amount": 1,
        "quest_reward_item_name": "Pokemon",
        "quest_reward_pokemon_name": "Surskit",
        "quest_reward_pokemon_id": 283,
        "quest_reward_item_id": 0,
        "pokestops": [
            {
                "pokestop_id": "16eb62ffd4774ebfaea1a2c242368a89.16",
                "name": "Black Cat",
                "latitude": 39.745372,
                "longitude": -8.807148
            }
        ]
    },
    {
        "quest_description": "Catch 5 Pok\u00e9mon with Weather Boost",
        "quest_reward": "Vanillite",
        "quest_reward_type": "Pokemon",
        "quest_reward_amount": 1,
        "quest_reward_item_name": "Pokemon",
        "quest_reward_pokemon_name": "Vanillite",
        "quest_reward_pokemon_id": 582,
        "quest_reward_item_id": 0,
        "pokestops": [
            {
                "pokestop_id": "17b2cd0ad9d434b8a10e960f0b4171ba.16",
                "name": "Parque desportivo de S.Rom\u00e3o",
                "latitude": 39.735758,
                "longitude": -8.795726
            }
        ]
    },
    {
        "quest_description": "Catch 10 Fire-type Pok\u00e9mon",
        "quest_reward": "10 Blaziken Mega Energy",
        "quest_reward_type": "Energy",
        "quest_reward_amount": 10,
        "quest_reward_item_name": "Mega Energy",
        "quest_reward_pokemon_name": "Blaziken",
        "quest_reward_pokemon_id": 257,
        "quest_reward_item_id": 0,
        "pokestops": [
            {
                "pokestop_id": "1846373feb73459994ce56162712ff83.16",
                "name": "Correios Marrazes",
                "latitude": 39.753807,
                "longitude": -8.81209
            }
        ]
    },
    {
        "quest_description": "Catch 10 Grass-type Pok\u00e9mon",
        "quest_reward": "10 Venusaur Mega Energy",
        "quest_reward_type": "Energy",
        "quest_reward_amount": 10,
        "quest_reward_item_name": "Mega Energy",
        "quest_reward_pokemon_name": "Venusaur",
        "quest_reward_pokemon_id": 3,
        "quest_reward_item_id": 0,
        "pokestops": [
            {
                "pokestop_id": "23076c7b2d5e3d209916143b5207e5b3.16",
                "name": "Soneto da Casa",
                "latitude": 39.733913,
                "longitude": -8.80966
            }
        ]
    },
    {
        "quest_description": "Catch 5 Pok\u00e9mon with Weather Boost",
        "quest_reward": "1 Pinap Berry",
        "quest_reward_type": "Item",
        "quest_reward_amount": 1,
        "quest_reward_item_name": "Pinap Berry",
        "quest_reward_pokemon_name": "",
        "quest_reward_pokemon_id": "000",
        "quest_reward_item_id": 705,
        "pokestops": [
            {
                "pokestop_id": "24cfefaa5f093740869a039a16a428a2.16",
                "name": "Parque Infantil Beira Rio",
                "latitude": 39.739953,
                "longitude": -8.80073
            }
        ]
    },
    {
        "quest_description": "Catch 10 Pok\u00e9mon",
        "quest_reward": "200 Stardust",
        "quest_reward_type": "Stardust",
        "quest_reward_amount": 200,
        "quest_reward_item_name": "Stardust",
        "quest_reward_pokemon_name": "",
        "quest_reward_pokemon_id": "000",
        "quest_reward_item_id": 0,
        "pokestops": [
            {
                "pokestop_id": "25da6da86d7b4e059a263ea1ba0947bf.16",
                "name": "Pharmacia",
                "latitude": 39.745802,
                "longitude": -8.807245
            },
            {
                "pokestop_id": "d8f921022177335fb4f14dcd5650f88d.16",
                "name": "Ricardo Pereira Studio",
                "latitude": 39.743409,
                "longitude": -8.800661
            }
        ]
    },
    {
        "quest_description": "Catch 5 Pok\u00e9mon with Weather Boost",
        "quest_reward": "Roggenrola",
        "quest_reward_type": "Pokemon",
        "quest_reward_amount": 1,
        "quest_reward_item_name": "Pokemon",
        "quest_reward_pokemon_name": "Roggenrola",
        "quest_reward_pokemon_id": 524,
        "quest_reward_item_id": 0,
        "pokestops": [
            {
                "pokestop_id": "2aa54838a48b45daacb94b17f7f32b81.16",
                "name": "Moagem Leiriense",
                "latitude": 39.74865,
                "longitude": -8.803723
            },
            {
                "pokestop_id": "bbc92efd9d1241c8b25bcfdfd74be4e8.11",
                "name": "Est\u00e1tua Lu\u00eds de Cam\u00f5es",
                "latitude": 39.744778,
                "longitude": -8.80632
            }
        ]
    },
    {
        "quest_description": "Catch 10 Pok\u00e9mon",
        "quest_reward": "Morelull",
        "quest_reward_type": "Pokemon",
        "quest_reward_amount": 1,
        "quest_reward_item_name": "Pokemon",
        "quest_reward_pokemon_name": "Morelull",
        "quest_reward_pokemon_id": 755,
        "quest_reward_item_id": 0,
        "pokestops": [
            {
                "pokestop_id": "399426cd8ff340e6b273e3bede1d39bd.16",
                "name": "Congrega\u00e7\u00e3o Crist\u00e3 em Portugal.",
                "latitude": 39.746828,
                "longitude": -8.814662
            },
            {
                "pokestop_id": "6641122bc0ea406f917adfe1cfbd22e6.11",
                "name": "Mercado Municipal",
                "latitude": 39.749213,
                "longitude": -8.8064
            }
        ]
    },
    {
        "quest_description": "Catch 5 Pok\u00e9mon with Weather Boost",
        "quest_reward": "5 Pok\u00e9 Ball",
        "quest_reward_type": "Item",
        "quest_reward_amount": 5,
        "quest_reward_item_name": "Pok\u00e9 Ball",
        "quest_reward_pokemon_name": "",
        "quest_reward_pokemon_id": "000",
        "quest_reward_item_id": 1,
        "pokestops": [
            {
                "pokestop_id": "3bbc897a1d6a4a6194f3326b30204c44.16",
                "name": "O Gladiador",
                "latitude": 39.746592,
                "longitude": -8.803601
            },
            {
                "pokestop_id": "401aa5fe5e2a4ac2b7ed091070a5dc86.16",
                "name": "Skate Parque Do Parque da Cerca",
                "latitude": 39.74986,
                "longitude": -8.935551
            },
            {
                "pokestop_id": "99648d7b7047482f9ff6c4a1c3db847c.16",
                "name": "CAL",
                "latitude": 39.741024,
                "longitude": -8.806283
            }
        ]
    },
    {
        "quest_description": "Catch 10 Grass-type Pok\u00e9mon",
        "quest_reward": "5 Great Ball",
        "quest_reward_type": "Item",
        "quest_reward_amount": 5,
        "quest_reward_item_name": "Great Ball",
        "quest_reward_pokemon_name": "",
        "quest_reward_pokemon_id": "000",
        "quest_reward_item_id": 2,
        "pokestops": [
            {
                "pokestop_id": "3dde03090bbf41dd8051072fd518992c.16",
                "name": "I P Leiria",
                "latitude": 39.744915,
                "longitude": -8.811439
            }
        ]
    },
    {
        "quest_description": "Catch 10 Pok\u00e9mon",
        "quest_reward": "3 Razz Berry",
        "quest_reward_type": "Item",
        "quest_reward_amount": 3,
        "quest_reward_item_name": "Razz Berry",
        "quest_reward_pokemon_name": "",
        "quest_reward_pokemon_id": "000",
        "quest_reward_item_id": 701,
        "pokestops": [
            {
                "pokestop_id": "476cd168efed4d6e89a22886cad6debf.16",
                "name": "Gin\u00e1sio ao Ar Livre",
                "latitude": 39.750817,
                "longitude": -8.929649
            },
            {
                "pokestop_id": "be66319f728f4260a674aac7952bb89f.16",
                "name": "Edif\u00edcio Ferro de Engomar",
                "latitude": 39.740629,
                "longitude": -8.802995
            }
        ]
    },
    {
        "quest_description": "Use 5 Berries to help catch Pok\u00e9mon",
        "quest_reward": "500 Stardust",
        "quest_reward_type": "Stardust",
        "quest_reward_amount": 500,
        "quest_reward_item_name": "Stardust",
        "quest_reward_pokemon_name": "",
        "quest_reward_pokemon_id": "000",
        "quest_reward_item_id": 0,
        "pokestops": [
            {
                "pokestop_id": "49c04382873542c79044fd2f8014bd55.16",
                "name": "Atl\u00e9tico Clube Marinhense",
                "latitude": 39.748748,
                "longitude": -8.936854
            },
            {
                "pokestop_id": "5d26a723ff7a4e7aa901e7f1b9179b5d.16",
                "name": "Lago Santo Agostinho",
                "latitude": 39.74149,
                "longitude": -8.801741
            },
            {
                "pokestop_id": "e516df4fe5f24dbe9bdc13861a72792b.16",
                "name": "Zona de lazer",
                "latitude": 39.737598,
                "longitude": -8.928606
            },
            {
                "pokestop_id": "ef40698afdf14bf2807803376584a143.16",
                "name": "Pa\u00e7o D.Jo\u00e3o I",
                "latitude": 39.746508,
                "longitude": -8.809111
            }
        ]
    },
    {
        "quest_description": "Catch 10 Normal-type Pok\u00e9mon",
        "quest_reward": "10 Pidgeot Mega Energy",
        "quest_reward_type": "Energy",
        "quest_reward_amount": 10,
        "quest_reward_item_name": "Mega Energy",
        "quest_reward_pokemon_name": "Pidgeot",
        "quest_reward_pokemon_id": 18,
        "quest_reward_item_id": 0,
        "pokestops": [
            {
                "pokestop_id": "4dbc1059dc043532829dda66e5d5ab5b.16",
                "name": "Caixa Postal CTT",
                "latitude": 39.742178,
                "longitude": -8.798332
            },
            {
                "pokestop_id": "b13a690750374016ab376f8a645094a7.16",
                "name": "Torre Agua Leiria",
                "latitude": 39.743319,
                "longitude": -8.799232
            }
        ]
    },
    {
        "quest_description": "Catch 5 Grass- or Ice-type Pok\u00e9mon",
        "quest_reward": "Smoliv",
        "quest_reward_type": "Pokemon",
        "quest_reward_amount": 1,
        "quest_reward_item_name": "Pokemon",
        "quest_reward_pokemon_name": "Smoliv",
        "quest_reward_pokemon_id": 928,
        "quest_reward_item_id": 0,
        "pokestops": [
            {
                "pokestop_id": "576f4061b2764fc1b3d0c4321299f83b.16",
                "name": "Playcity 003",
                "latitude": 39.740875,
                "longitude": -8.801093
            }
        ]
    },
    {
        "quest_description": "Catch 10 Normal-type Pok\u00e9mon",
        "quest_reward": "500 Stardust",
        "quest_reward_type": "Stardust",
        "quest_reward_amount": 500,
        "quest_reward_item_name": "Stardust",
        "quest_reward_pokemon_name": "",
        "quest_reward_pokemon_id": "000",
        "quest_reward_item_id": 0,
        "pokestops": [
            {
                "pokestop_id": "58c2e26bd5e34983b8b96b7d6334f54f.16",
                "name": "Jardins do Lis Galerias",
                "latitude": 39.750761,
                "longitude": -8.805877
            },
            {
                "pokestop_id": "9baafb93f8093e628262f96c06541c99.16",
                "name": "A Pobreza N\u00e3o \u00e9 Cor de Rosa",
                "latitude": 39.743218,
                "longitude": -8.812164
            }
        ]
    },
    {
        "quest_description": "Catch 10 Pok\u00e9mon",
        "quest_reward": "5 Pok\u00e9 Ball",
        "quest_reward_type": "Item",
        "quest_reward_amount": 5,
        "quest_reward_item_name": "Pok\u00e9 Ball",
        "quest_reward_pokemon_name": "",
        "quest_reward_pokemon_id": "000",
        "quest_reward_item_id": 1,
        "pokestops": [
            {
                "pokestop_id": "5b30d5cc95af495c8066d9675b25ae77.16",
                "name": "Lonac 2017",
                "latitude": 39.744206,
                "longitude": -8.812656
            }
        ]
    },
    {
        "quest_description": "Catch 5 Pok\u00e9mon with Weather Boost",
        "quest_reward": "200 Stardust",
        "quest_reward_type": "Stardust",
        "quest_reward_amount": 200,
        "quest_reward_item_name": "Stardust",
        "quest_reward_pokemon_name": "",
        "quest_reward_pokemon_id": "000",
        "quest_reward_item_id": 0,
        "pokestops": [
            {
                "pokestop_id": "5f459ededcb34ad49531ba905abc2880.16",
                "name": "Pai Natal Lar\u00e1pio",
                "latitude": 39.73156,
                "longitude": -8.823204
            }
        ]
    },
    {
        "quest_description": "Catch 5 Pok\u00e9mon with Weather Boost",
        "quest_reward": "3 Razz Berry",
        "quest_reward_type": "Item",
        "quest_reward_amount": 3,
        "quest_reward_item_name": "Razz Berry",
        "quest_reward_pokemon_name": "",
        "quest_reward_pokemon_id": "000",
        "quest_reward_item_id": 701,
        "pokestops": [
            {
                "pokestop_id": "60e0ad8ad66d44b6aaac09f808924508.16",
                "name": "Bairro dos Anjos",
                "latitude": 39.744958,
                "longitude": -8.804361
            },
            {
                "pokestop_id": "63f82eedfebe4f3ba61cad72f2d0644f.16",
                "name": "Junta De Freguesia Leiria",
                "latitude": 39.743562,
                "longitude": -8.804606
            }
        ]
    },
    {
        "quest_description": "Catch 10 Grass-type Pok\u00e9mon",
        "quest_reward": "6 Razz Berry",
        "quest_reward_type": "Item",
        "quest_reward_amount": 6,
        "quest_reward_item_name": "Razz Berry",
        "quest_reward_pokemon_name": "",
        "quest_reward_pokemon_id": "000",
        "quest_reward_item_id": 701,
        "pokestops": [
            {
                "pokestop_id": "64028475605436c098d172cef7a27671.16",
                "name": "Arquivo Municipal de Leiria",
                "latitude": 39.731487,
                "longitude": -8.794807
            },
            {
                "pokestop_id": "b572ea0faae6348092bcf609be3e4bad.16",
                "name": "Caixa Postal CTT - Cristal Atrium",
                "latitude": 39.747021,
                "longitude": -8.936766
            }
        ]
    },
    {
        "quest_description": "Catch 10 Grass-type Pok\u00e9mon",
        "quest_reward": "500 Stardust",
        "quest_reward_type": "Stardust",
        "quest_reward_amount": 500,
        "quest_reward_item_name": "Stardust",
        "quest_reward_pokemon_name": "",
        "quest_reward_pokemon_id": "000",
        "quest_reward_item_id": 0,
        "pokestops": [
            {
                "pokestop_id": "642c0f5b7ba6396b8c97fbd5bc5b4131.16",
                "name": "Leiria Shopping",
                "latitude": 39.732373,
                "longitude": -8.824896
            }
        ]
    },
    {
        "quest_description": "Use 5 Berries to help catch Pok\u00e9mon",
        "quest_reward": "Dwebble",
        "quest_reward_type": "Pokemon",
        "quest_reward_amount": 1,
        "quest_reward_item_name": "Pokemon",
        "quest_reward_pokemon_name": "Dwebble",
        "quest_reward_pokemon_id": 557,
        "quest_reward_item_id": 0,
        "pokestops": [
            {
                "pokestop_id": "65f5766b89563c9ba8bab5894ffd9e4e.16",
                "name": "Sede PSD Leiria",
                "latitude": 39.742459,
                "longitude": -8.808694
            },
            {
                "pokestop_id": "78b6871979994648b86c2b8e50ba0eb5.16",
                "name": "Janelas Santo Agostinho",
                "latitude": 39.740857,
                "longitude": -8.801746
            },
            {
                "pokestop_id": "ce1e9a64fd4e473290950246fac35c13.11",
                "name": "Est\u00e1dio Municipal de Leiria",
                "latitude": 39.749735,
                "longitude": -8.812954
            }
        ]
    },
    {
        "quest_description": "Catch 5 Pok\u00e9mon",
        "quest_reward": "Cubchoo",
        "quest_reward_type": "Pokemon",
        "quest_reward_amount": 1,
        "quest_reward_item_name": "Pokemon",
        "quest_reward_pokemon_name": "Cubchoo",
        "quest_reward_pokemon_id": 613,
        "quest_reward_item_id": 0,
        "pokestops": [
            {
                "pokestop_id": "6911dd91c1994c11a3ce259f0947fec5.16",
                "name": "Ponte pedestre do parque da Bernardas",
                "latitude": 39.737402,
                "longitude": -8.928949
            },
            {
                "pokestop_id": "ea049e0330ff36d794e53891c4de8d45.16",
                "name": "Confer\u00eancia de S. Vicente Paulo",
                "latitude": 39.750114,
                "longitude": -8.92967
            }
        ]
    },
    {
        "quest_description": "Catch 7 Pok\u00e9mon",
        "quest_reward": "Stufful",
        "quest_reward_type": "Pokemon",
        "quest_reward_amount": 1,
        "quest_reward_item_name": "Pokemon",
        "quest_reward_pokemon_name": "Stufful",
        "quest_reward_pokemon_id": 759,
        "quest_reward_item_id": 0,
        "pokestops": [
            {
                "pokestop_id": "6edbcc878c3c30fcb3e18084be80272a.16",
                "name": "Centro Comercial Olhalvas Park",
                "latitude": 39.741431,
                "longitude": -8.79645
            },
            {
                "pokestop_id": "8139220c2677423f81f5be907a3e94c4.16",
                "name": "Sede N\u00facleo Sporting",
                "latitude": 39.750953,
                "longitude": -8.932885
            }
        ]
    },
    {
        "quest_description": "Use 5 Berries to help catch Pok\u00e9mon",
        "quest_reward": "6 Razz Berry",
        "quest_reward_type": "Item",
        "quest_reward_amount": 6,
        "quest_reward_item_name": "Razz Berry",
        "quest_reward_pokemon_name": "",
        "quest_reward_pokemon_id": "000",
        "quest_reward_item_id": 701,
        "pokestops": [
            {
                "pokestop_id": "7065b593394b4d08b1b8c86d197794e5.16",
                "name": "Ponte pedestre do Parque dos m\u00e1rtires do colonialismo.",
                "latitude": 39.745489,
                "longitude": -8.933253
            },
            {
                "pokestop_id": "9f3d5e1703b74483b3d6625f162b2842.16",
                "name": "Ponte pedonal sul do Parque das Bernardas",
                "latitude": 39.737116,
                "longitude": -8.928597
            },
            {
                "pokestop_id": "fc7d5b3852b847f497461aa830d88bde.16",
                "name": "A\u00e7ude Da Fonte Quente",
                "latitude": 39.747803,
                "longitude": -8.802251
            }
        ]
    },
    {
        "quest_description": "Catch 7 Pok\u00e9mon",
        "quest_reward": "Magikarp",
        "quest_reward_type": "Pokemon",
        "quest_reward_amount": 1,
        "quest_reward_item_name": "Pokemon",
        "quest_reward_pokemon_name": "Magikarp",
        "quest_reward_pokemon_id": 129,
        "quest_reward_item_id": 0,
        "pokestops": [
            {
                "pokestop_id": "74c2b093f88f4960b4c7500711e97828.16",
                "name": "parque Tenente Coronel Jaime Filipe Da Fonseca",
                "latitude": 39.745038,
                "longitude": -8.804716
            }
        ]
    },
    {
        "quest_description": "Catch 10 Water-type Pok\u00e9mon",
        "quest_reward": "10 Swampert Mega Energy",
        "quest_reward_type": "Energy",
        "quest_reward_amount": 10,
        "quest_reward_item_name": "Mega Energy",
        "quest_reward_pokemon_name": "Swampert",
        "quest_reward_pokemon_id": 260,
        "quest_reward_item_id": 0,
        "pokestops": [
            {
                "pokestop_id": "7ce99cdeda41439eb6de9133392a5262.16",
                "name": "Cabine de Leitura - Trokakioske",
                "latitude": 39.744527,
                "longitude": -8.807312
            },
            {
                "pokestop_id": "dd77a59686d64c538ef83fc8c6375162.16",
                "name": "Janelas do Jardim da Almuinha",
                "latitude": 39.751734,
                "longitude": -8.80984
            }
        ]
    },
    {
        "quest_description": "Catch 10 Pok\u00e9mon with Weather Boost",
        "quest_reward": "2 Pinap Berry",
        "quest_reward_type": "Item",
        "quest_reward_amount": 2,
        "quest_reward_item_name": "Pinap Berry",
        "quest_reward_pokemon_name": "",
        "quest_reward_pokemon_id": "000",
        "quest_reward_item_id": 705,
        "pokestops": [
            {
                "pokestop_id": "80fff49f00003aadbf32302a836e98ba.16",
                "name": "Rota Arquitect\u00f3nica - Edif\u00edcio Barros Santa Rita",
                "latitude": 39.742059,
                "longitude": -8.808031
            }
        ]
    },
    {
        "quest_description": "Catch 7 different species of Pok\u00e9mon",
        "quest_reward": "Golett",
        "quest_reward_type": "Pokemon",
        "quest_reward_amount": 1,
        "quest_reward_item_name": "Pokemon",
        "quest_reward_pokemon_name": "Golett",
        "quest_reward_pokemon_id": 622,
        "quest_reward_item_id": 0,
        "pokestops": [
            {
                "pokestop_id": "830aef5d6696357d8f2ba2d9492ed50f.16",
                "name": "Campo Polidesportivo",
                "latitude": 39.732954,
                "longitude": -8.809802
            },
            {
                "pokestop_id": "b081ac76889c34449df7d48ebb87c1e4.16",
                "name": "Glove x 400mI",
                "latitude": 39.74775,
                "longitude": -8.807233
            },
            {
                "pokestop_id": "ed033216b8ae4a3e96eff61d08cf1bab.16",
                "name": "Ringue de futebol",
                "latitude": 39.730853,
                "longitude": -8.811065
            }
        ]
    },
    {
        "quest_description": "Catch 5 Grass- or Ice-type Pok\u00e9mon",
        "quest_reward": "Vanillite",
        "quest_reward_type": "Pokemon",
        "quest_reward_amount": 1,
        "quest_reward_item_name": "Pokemon",
        "quest_reward_pokemon_name": "Vanillite",
        "quest_reward_pokemon_id": 582,
        "quest_reward_item_id": 0,
        "pokestops": [
            {
                "pokestop_id": "8c20f9c9b65b384ea6311422e708bcd1.16",
                "name": "Parque Verde de Leiria",
                "latitude": 39.741617,
                "longitude": -8.819755
            }
        ]
    },
    {
        "quest_description": "Catch 10 Grass-type Pok\u00e9mon",
        "quest_reward": "2 Pinap Berry",
        "quest_reward_type": "Item",
        "quest_reward_amount": 2,
        "quest_reward_item_name": "Pinap Berry",
        "quest_reward_pokemon_name": "",
        "quest_reward_pokemon_id": "000",
        "quest_reward_item_id": 705,
        "pokestops": [
            {
                "pokestop_id": "8d9c226f1c954eb9ba79a5672405dbb5.16",
                "name": "Homenagem \u00c0 Ind\u00fastria dos Pl\u00e1sticos",
                "latitude": 39.750529,
                "longitude": -8.803749
            }
        ]
    },
    {
        "quest_description": "Catch 10 Pok\u00e9mon with Weather Boost",
        "quest_reward": "500 Stardust",
        "quest_reward_type": "Stardust",
        "quest_reward_amount": 500,
        "quest_reward_item_name": "Stardust",
        "quest_reward_pokemon_name": "",
        "quest_reward_pokemon_id": "000",
        "quest_reward_item_id": 0,
        "pokestops": [
            {
                "pokestop_id": "a80ebbee2a5e4f5dad3ae686f3b9b741.16",
                "name": "Mural Brisa do Lis",
                "latitude": 39.743468,
                "longitude": -8.812448
            }
        ]
    },
    {
        "quest_description": "Catch 10 Pok\u00e9mon",
        "quest_reward": "1 Pinap Berry",
        "quest_reward_type": "Item",
        "quest_reward_amount": 1,
        "quest_reward_item_name": "Pinap Berry",
        "quest_reward_pokemon_name": "",
        "quest_reward_pokemon_id": "000",
        "quest_reward_item_id": 705,
        "pokestops": [
            {
                "pokestop_id": "a9aecff3187e48e6bc006f1a2fd4ee5a.16",
                "name": "Arco da Nossa Senhora Da Encarna\u00e7\u00e3o",
                "latitude": 39.739299,
                "longitude": -8.801276
            },
            {
                "pokestop_id": "c7e8bf75d42241c18158406287c71bae.16",
                "name": "Ru\u00ednas Capela Santo Ant\u00f3nio Carrascal",
                "latitude": 39.745123,
                "longitude": -8.797432
            }
        ]
    },
    {
        "quest_description": "Catch 5 Pok\u00e9mon with Weather Boost",
        "quest_reward": "Hippopotas",
        "quest_reward_type": "Pokemon",
        "quest_reward_amount": 1,
        "quest_reward_item_name": "Pokemon",
        "quest_reward_pokemon_name": "Hippopotas",
        "quest_reward_pokemon_id": 449,
        "quest_reward_item_id": 0,
        "pokestops": [
            {
                "pokestop_id": "b4d3ed3c70633b00a060f057fac0061e.16",
                "name": "Wellness life",
                "latitude": 39.751779,
                "longitude": -8.929718
            }
        ]
    },
    {
        "quest_description": "Catch 10 Water-type Pok\u00e9mon",
        "quest_reward": "500 Stardust",
        "quest_reward_type": "Stardust",
        "quest_reward_amount": 500,
        "quest_reward_item_name": "Stardust",
        "quest_reward_pokemon_name": "",
        "quest_reward_pokemon_id": "000",
        "quest_reward_item_id": 0,
        "pokestops": [
            {
                "pokestop_id": "c194e76186764926aed5179fbd77c49c.16",
                "name": "Sede do Partido Social Democrata da Marinha Grande",
                "latitude": 39.746712,
                "longitude": -8.928824
            }
        ]
    },
    {
        "quest_description": "Catch 5 Pok\u00e9mon with Weather Boost",
        "quest_reward": "Poliwag",
        "quest_reward_type": "Pokemon",
        "quest_reward_amount": 1,
        "quest_reward_item_name": "Pokemon",
        "quest_reward_pokemon_name": "Poliwag",
        "quest_reward_pokemon_id": 60,
        "quest_reward_item_id": 0,
        "pokestops": [
            {
                "pokestop_id": "c3c8a7b519bd349b96df337260957971.16",
                "name": "Sociedade Columb\u00f3fila Marinhense",
                "latitude": 39.748494,
                "longitude": -8.932563
            }
        ]
    },
    {
        "quest_description": "Catch 7 Pok\u00e9mon",
        "quest_reward": "Wimpod",
        "quest_reward_type": "Pokemon",
        "quest_reward_amount": 1,
        "quest_reward_item_name": "Pokemon",
        "quest_reward_pokemon_name": "Wimpod",
        "quest_reward_pokemon_id": 767,
        "quest_reward_item_id": 0,
        "pokestops": [
            {
                "pokestop_id": "cfdf82394f2d4d97a5ce70abf1a890ca.16",
                "name": "Assembleia de Deus",
                "latitude": 39.745074,
                "longitude": -8.936455
            }
        ]
    },
    {
        "quest_description": "Catch 10 Pok\u00e9mon with Weather Boost",
        "quest_reward": "6 Razz Berry",
        "quest_reward_type": "Item",
        "quest_reward_amount": 6,
        "quest_reward_item_name": "Razz Berry",
        "quest_reward_pokemon_name": "",
        "quest_reward_pokemon_id": "000",
        "quest_reward_item_id": 701,
        "pokestops": [
            {
                "pokestop_id": "d224abae8949373a91cda0a9128462cd.16",
                "name": "Barcos da Costa",
                "latitude": 39.73964,
                "longitude": -8.805776
            }
        ]
    },
    {
        "quest_description": "Catch 10 Pok\u00e9mon with Weather Boost",
        "quest_reward": "5 Great Ball",
        "quest_reward_type": "Item",
        "quest_reward_amount": 5,
        "quest_reward_item_name": "Great Ball",
        "quest_reward_pokemon_name": "",
        "quest_reward_pokemon_id": "000",
        "quest_reward_item_id": 2,
        "pokestops": [
            {
                "pokestop_id": "eb236851e5b8353aa9a7a7601c550fd6.16",
                "name": "Liz ao Quadro - Art Galery",
                "latitude": 39.748424,
                "longitude": -8.802439
            }
        ]
    }
]