[
    {
        "quest_description": "Make 3 Nice Throws in a row",
        "quest_reward": "2 Ultra Ball",
        "quest_reward_type": "Item",
        "quest_reward_amount": 2,
        "quest_reward_item_name": "Ultra Ball",
        "quest_reward_pokemon_name": "",
        "quest_reward_pokemon_id": "000",
        "quest_reward_item_id": 3,
        "pokestops": [
            {
                "pokestop_id": "032b9f33369a433bb4c8b0bb3dc0f5b3.16",
                "name": "Globo",
                "latitude": 39.75366,
                "longitude": -8.812859
            },
            {
                "pokestop_id": "176cb9f808b441daae85466c3d053623.11",
                "name": "Fonte Luminosa",
                "latitude": 39.743649,
                "longitude": -8.806831
            }
        ]
    },
    {
        "quest_description": "Make 5 Great Throws",
        "quest_reward": "Mankey",
        "quest_reward_type": "Pokemon",
        "quest_reward_amount": 1,
        "quest_reward_item_name": "Pokemon",
        "quest_reward_pokemon_name": "Mankey",
        "quest_reward_pokemon_id": 56,
        "quest_reward_item_id": 0,
        "pokestops": [
            {
                "pokestop_id": "06030e41449c4302874baae88549b655.16",
                "name": "Correios Her\u00f3is De Angola",
                "latitude": 39.747609,
                "longitude": -8.804195
            },
            {
                "pokestop_id": "3c3affed92033d50b8f0202713d8a53e.16",
                "name": "Villa Portela - Casa D'Artes",
                "latitude": 39.741224,
                "longitude": -8.809235
            },
            {
                "pokestop_id": "b4fc631c4b4133bb859a6dcbfb06a469.16",
                "name": "Marco de Correios CTT",
                "latitude": 39.752895,
                "longitude": -8.805935
            },
            {
                "pokestop_id": "e45e96f79eee4dd5b32db03fd04c4191.16",
                "name": "Centro Comercial D.Dinis",
                "latitude": 39.742971,
                "longitude": -8.809768
            }
        ]
    },
    {
        "quest_description": "Make an Excellent Throw",
        "quest_reward": "2 Pinap Berry",
        "quest_reward_type": "Item",
        "quest_reward_amount": 2,
        "quest_reward_item_name": "Pinap Berry",
        "quest_reward_pokemon_name": "",
        "quest_reward_pokemon_id": "000",
        "quest_reward_item_id": 705,
        "pokestops": [
            {
                "pokestop_id": "0727712d36f33ead9a626d22bb911953.16",
                "name": "Baloico Santa Clara",
                "latitude": 39.73971,
                "longitude": -8.821638
            },
            {
                "pokestop_id": "be27a58579f64cae8b898b838163757b.16",
                "name": "VDesign",
                "latitude": 39.745756,
                "longitude": -8.807801
            },
            {
                "pokestop_id": "f1edf2dd4b33434186ddc331a2fb2ce3.11",
                "name": "Camara Municipal de Leiria",
                "latitude": 39.741093,
                "longitude": -8.810354
            }
        ]
    },
    {
        "quest_description": "Make 3 Great Throws",
        "quest_reward": "5 Pok\u00e9 Ball",
        "quest_reward_type": "Item",
        "quest_reward_amount": 5,
        "quest_reward_item_name": "Pok\u00e9 Ball",
        "quest_reward_pokemon_name": "",
        "quest_reward_pokemon_id": "000",
        "quest_reward_item_id": 1,
        "pokestops": [
            {
                "pokestop_id": "09211576d80e30c3b6007b0d72d8cf96.16",
                "name": "Azulejo Bairro dos Anjos",
                "latitude": 39.744443,
                "longitude": -8.804282
            },
            {
                "pokestop_id": "60d1f388534c3f81bcfeb1c529486086.16",
                "name": "Mesquita de Leiria",
                "latitude": 39.738707,
                "longitude": -8.805733
            },
            {
                "pokestop_id": "be810cdde01b3a9baa5454b7fba7511c.16",
                "name": "Tribunal do Trabalho de Leiria",
                "latitude": 39.739929,
                "longitude": -8.808784
            }
        ]
    },
    {
        "quest_description": "Make an Excellent Throw",
        "quest_reward": "5 Great Ball",
        "quest_reward_type": "Item",
        "quest_reward_amount": 5,
        "quest_reward_item_name": "Great Ball",
        "quest_reward_pokemon_name": "",
        "quest_reward_pokemon_id": "000",
        "quest_reward_item_id": 2,
        "pokestops": [
            {
                "pokestop_id": "097466c5212c4a0a81c4123a78445154.16",
                "name": "Mural \"Liberdade\"",
                "latitude": 39.745754,
                "longitude": -8.805297
            },
            {
                "pokestop_id": "6e16a724c20f4752b9b6cee03cfe329a.16",
                "name": "Nossa Senhora Imaculada Concei\u00e7\u00e3o",
                "latitude": 39.730732,
                "longitude": -8.808285
            },
            {
                "pokestop_id": "cfa99aca982c4d5594e91f019f507180.16",
                "name": "LeiriaMini - \u00c1rea Interativa",
                "latitude": 39.732346,
                "longitude": -8.824545
            }
        ]
    },
    {
        "quest_description": "Make 3 Nice Throws in a row",
        "quest_reward": "5 Great Ball",
        "quest_reward_type": "Item",
        "quest_reward_amount": 5,
        "quest_reward_item_name": "Great Ball",
        "quest_reward_pokemon_name": "",
        "quest_reward_pokemon_id": "000",
        "quest_reward_item_id": 2,
        "pokestops": [
            {
                "pokestop_id": "0a24790da0af39809c89230721e5ace9.16",
                "name": "Terra\u00e7o do Ateneu",
                "latitude": 39.739192,
                "longitude": -8.818713
            }
        ]
    },
    {
        "quest_description": "Make 3 Great Throws",
        "quest_reward": "3 Razz Berry",
        "quest_reward_type": "Item",
        "quest_reward_amount": 3,
        "quest_reward_item_name": "Razz Berry",
        "quest_reward_pokemon_name": "",
        "quest_reward_pokemon_id": "000",
        "quest_reward_item_id": 701,
        "pokestops": [
            {
                "pokestop_id": "0d8a08d8b1373ea6aa0dda39ef0333c1.16",
                "name": "m|i|mo - Museu da Imagem em Movimento",
                "latitude": 39.747339,
                "longitude": -8.807318
            }
        ]
    },
    {
        "quest_description": "Make 3 Great Curveball Throws",
        "quest_reward": "10 Pok\u00e9 Ball",
        "quest_reward_type": "Item",
        "quest_reward_amount": 10,
        "quest_reward_item_name": "Pok\u00e9 Ball",
        "quest_reward_pokemon_name": "",
        "quest_reward_pokemon_id": "000",
        "quest_reward_item_id": 1,
        "pokestops": [
            {
                "pokestop_id": "14a69ce370fb46f88261e19bbc2101cb.16",
                "name": "Biblioteca Municipal Afonso Lopes Vieira",
                "latitude": 39.743917,
                "longitude": -8.810087
            }
        ]
    },
    {
        "quest_description": "Make 5 Great Curveball Throws",
        "quest_reward": "Cranidos",
        "quest_reward_type": "Pokemon",
        "quest_reward_amount": 1,
        "quest_reward_item_name": "Pokemon",
        "quest_reward_pokemon_name": "Cranidos",
        "quest_reward_pokemon_id": 408,
        "quest_reward_item_id": 0,
        "pokestops": [
            {
                "pokestop_id": "17bd4c9f924b46578bbb4bbf28e7b6e9.16",
                "name": "Fonte De \u00c1gua Quente",
                "latitude": 39.747102,
                "longitude": -8.801658
            },
            {
                "pokestop_id": "44c4e82a70a73e23a89ed45b8d7d1e88.16",
                "name": "Caixa Postal dos CTT - Quinta da Matinha",
                "latitude": 39.755207,
                "longitude": -8.806823
            },
            {
                "pokestop_id": "490174996655472e998bccb559694a1b.16",
                "name": "Bordalo II",
                "latitude": 39.742515,
                "longitude": -8.80218
            },
            {
                "pokestop_id": "59e2f6466c39394db919bde10c6df0c6.16",
                "name": "O Prisioneiro",
                "latitude": 39.744766,
                "longitude": -8.81039
            },
            {
                "pokestop_id": "948d8db4d6ef46d7aecb05bf24a888f8.16",
                "name": "CTT Leiria Plaza",
                "latitude": 39.742146,
                "longitude": -8.810426
            },
            {
                "pokestop_id": "94c85bca573c49d1b801c77c04693736.16",
                "name": "Ponte El-Rei D. Dinis",
                "latitude": 39.743323,
                "longitude": -8.804477
            },
            {
                "pokestop_id": "c0b71dcb032c35768adff51494b564f6.16",
                "name": "Caixa Postal Leiria - Galerias S\u00e3o Jos\u00e9",
                "latitude": 39.739793,
                "longitude": -8.808255
            },
            {
                "pokestop_id": "c5e96e69dbd13b3eab5f62d3ff424bec.16",
                "name": "Gin\u00e1sio Fit On Move",
                "latitude": 39.745658,
                "longitude": -8.803177
            }
        ]
    },
    {
        "quest_description": "Make 5 Nice Throws",
        "quest_reward": "200 Stardust",
        "quest_reward_type": "Stardust",
        "quest_reward_amount": 200,
        "quest_reward_item_name": "Stardust",
        "quest_reward_pokemon_name": "",
        "quest_reward_pokemon_id": "000",
        "quest_reward_item_id": 0,
        "pokestops": [
            {
                "pokestop_id": "22af41a0de094b3b9a328d93dc104eff.16",
                "name": "Lis Shopping",
                "latitude": 39.739681,
                "longitude": -8.817837
            },
            {
                "pokestop_id": "b081ac76889c34449df7d48ebb87c1e4.16",
                "name": "Glove x 400mI",
                "latitude": 39.74775,
                "longitude": -8.807233
            },
            {
                "pokestop_id": "d507cf11ba724b0e99127ed0e11b6597.16",
                "name": "Lenda do Lis e do Lena",
                "latitude": 39.743468,
                "longitude": -8.8068
            }
        ]
    },
    {
        "quest_description": "Make 5 Nice Throws",
        "quest_reward": "Sudowoodo",
        "quest_reward_type": "Pokemon",
        "quest_reward_amount": 1,
        "quest_reward_item_name": "Pokemon",
        "quest_reward_pokemon_name": "Sudowoodo",
        "quest_reward_pokemon_id": 185,
        "quest_reward_item_id": 0,
        "pokestops": [
            {
                "pokestop_id": "24cfefaa5f093740869a039a16a428a2.16",
                "name": "Parque Infantil Beira Rio",
                "latitude": 39.739953,
                "longitude": -8.80073
            }
        ]
    },
    {
        "quest_description": "Make 5 Nice Throws",
        "quest_reward": "5 Pok\u00e9 Ball",
        "quest_reward_type": "Item",
        "quest_reward_amount": 5,
        "quest_reward_item_name": "Pok\u00e9 Ball",
        "quest_reward_pokemon_name": "",
        "quest_reward_pokemon_id": "000",
        "quest_reward_item_id": 1,
        "pokestops": [
            {
                "pokestop_id": "25a0330c10104e74a733559e8c6d11a2.16",
                "name": "Centro Desportivo Juve Lis",
                "latitude": 39.731097,
                "longitude": -8.794939
            },
            {
                "pokestop_id": "484d1bcbc0a443cb933cf338d4aa6e43.16",
                "name": "Engenharia Autom\u00f3vel",
                "latitude": 39.733074,
                "longitude": -8.821522
            },
            {
                "pokestop_id": "6f488a3619b54eee94b6141b734aa768.16",
                "name": "Monumento Afonso Lopes Vieira",
                "latitude": 39.740246,
                "longitude": -8.81261
            }
        ]
    },
    {
        "quest_description": "Make 5 Curveball Throws in a row",
        "quest_reward": "5 Great Ball",
        "quest_reward_type": "Item",
        "quest_reward_amount": 5,
        "quest_reward_item_name": "Great Ball",
        "quest_reward_pokemon_name": "",
        "quest_reward_pokemon_id": "000",
        "quest_reward_item_id": 2,
        "pokestops": [
            {
                "pokestop_id": "29449a7785e732ce9e8046d7c5ac0612.16",
                "name": "O Diab\u00f3lico",
                "latitude": 39.729536,
                "longitude": -8.812971
            }
        ]
    },
    {
        "quest_description": "Make 2 Nice Curveball Throws in a row",
        "quest_reward": "3 Razz Berry",
        "quest_reward_type": "Item",
        "quest_reward_amount": 3,
        "quest_reward_item_name": "Razz Berry",
        "quest_reward_pokemon_name": "",
        "quest_reward_pokemon_id": "000",
        "quest_reward_item_id": 701,
        "pokestops": [
            {
                "pokestop_id": "2eb6fcf025c9474d971550339c9512ae.11",
                "name": "Correios Leiria (Post Office)",
                "latitude": 39.743073,
                "longitude": -8.808473
            }
        ]
    },
    {
        "quest_description": "Make 3 Great Throws",
        "quest_reward": "Elgyem",
        "quest_reward_type": "Pokemon",
        "quest_reward_amount": 1,
        "quest_reward_item_name": "Pokemon",
        "quest_reward_pokemon_name": "Elgyem",
        "quest_reward_pokemon_id": 605,
        "quest_reward_item_id": 0,
        "pokestops": [
            {
                "pokestop_id": "3c83b4e51d5434168b1438aaf1ff432c.16",
                "name": "BicLis - Esta\u00e7\u00e3o das Piscinas",
                "latitude": 39.749826,
                "longitude": -8.809016
            }
        ]
    },
    {
        "quest_description": "Make 5 Great Throws",
        "quest_reward": "Machop",
        "quest_reward_type": "Pokemon",
        "quest_reward_amount": 1,
        "quest_reward_item_name": "Pokemon",
        "quest_reward_pokemon_name": "Machop",
        "quest_reward_pokemon_id": 66,
        "quest_reward_item_id": 0,
        "pokestops": [
            {
                "pokestop_id": "40edfe553012431cbd444d3c3efcd87e.16",
                "name": "Dan'el E'me",
                "latitude": 39.740549,
                "longitude": -8.802441
            },
            {
                "pokestop_id": "a12d18e62f3c4c86981d2a6a4316c9a5.16",
                "name": "Homenagem aos Her\u00f3icos Soldados",
                "latitude": 39.746449,
                "longitude": -8.808147
            },
            {
                "pokestop_id": "b3356645cffd432abf254b1c58a5c593.16",
                "name": "Mural ESTG",
                "latitude": 39.734569,
                "longitude": -8.821932
            },
            {
                "pokestop_id": "cca9f6153cbc476eb8d40e954e2363fe.16",
                "name": "Rotary Club De Leiria",
                "latitude": 39.735202,
                "longitude": -8.798938
            }
        ]
    },
    {
        "quest_description": "Make 2 Nice Curveball Throws in a row",
        "quest_reward": "200 Stardust",
        "quest_reward_type": "Stardust",
        "quest_reward_amount": 200,
        "quest_reward_item_name": "Stardust",
        "quest_reward_pokemon_name": "",
        "quest_reward_pokemon_id": "000",
        "quest_reward_item_id": 0,
        "pokestops": [
            {
                "pokestop_id": "4e443bf8cf3a4dbe81ebdbc8415101bd.16",
                "name": "Centro de Linguas Chinesas",
                "latitude": 39.740291,
                "longitude": -8.811645
            }
        ]
    },
    {
        "quest_description": "Make 5 Great Curveball Throws",
        "quest_reward": "Shieldon",
        "quest_reward_type": "Pokemon",
        "quest_reward_amount": 1,
        "quest_reward_item_name": "Pokemon",
        "quest_reward_pokemon_name": "Shieldon",
        "quest_reward_pokemon_id": 410,
        "quest_reward_item_id": 0,
        "pokestops": [
            {
                "pokestop_id": "531b919d53b0427c88c55723aba7fa45.16",
                "name": "Campo Basketball",
                "latitude": 39.746655,
                "longitude": -8.802376
            },
            {
                "pokestop_id": "aedd1f2f1ad44401bedc5af66a1bad2a.16",
                "name": "Jungle Gym",
                "latitude": 39.749395,
                "longitude": -8.802482
            },
            {
                "pokestop_id": "ffa50f037c35420faa2db4536ac3bc3e.11",
                "name": "Est\u00e1tua Vacas",
                "latitude": 39.745118,
                "longitude": -8.804209
            }
        ]
    },
    {
        "quest_description": "Make 2 Nice Curveball Throws in a row",
        "quest_reward": "1 Pinap Berry",
        "quest_reward_type": "Item",
        "quest_reward_amount": 1,
        "quest_reward_item_name": "Pinap Berry",
        "quest_reward_pokemon_name": "",
        "quest_reward_pokemon_id": "000",
        "quest_reward_item_id": 705,
        "pokestops": [
            {
                "pokestop_id": "54bd503d2bee47c497072721aadf4da3.16",
                "name": "Marco CTT - Rua de Alcoba\u00e7a",
                "latitude": 39.741853,
                "longitude": -8.810621
            },
            {
                "pokestop_id": "d1624a91509e4723bdf14dc0d0cfaefa.16",
                "name": "Campus 1 - ESECS",
                "latitude": 39.739983,
                "longitude": -8.812123
            }
        ]
    },
    {
        "quest_description": "Make 2 Nice Curveball Throws in a row",
        "quest_reward": "5 Pok\u00e9 Ball",
        "quest_reward_type": "Item",
        "quest_reward_amount": 5,
        "quest_reward_item_name": "Pok\u00e9 Ball",
        "quest_reward_pokemon_name": "",
        "quest_reward_pokemon_id": "000",
        "quest_reward_item_id": 1,
        "pokestops": [
            {
                "pokestop_id": "5b411c74614a41499b344fed78efd2ec.16",
                "name": "Fonte Do Halton",
                "latitude": 39.747031,
                "longitude": -8.816442
            },
            {
                "pokestop_id": "7de0d62dd2884b5f987bb82c2f091548.16",
                "name": "D.Isabel",
                "latitude": 39.749043,
                "longitude": -8.80843
            }
        ]
    },
    {
        "quest_description": "Make 10 Nice Throws",
        "quest_reward": "Nidoran\u2640",
        "quest_reward_type": "Pokemon",
        "quest_reward_amount": 1,
        "quest_reward_item_name": "Pokemon",
        "quest_reward_pokemon_name": "Nidoran\u2640",
        "quest_reward_pokemon_id": 29,
        "quest_reward_item_id": 0,
        "pokestops": [
            {
                "pokestop_id": "642c0f5b7ba6396b8c97fbd5bc5b4131.16",
                "name": "Leiria Shopping",
                "latitude": 39.732373,
                "longitude": -8.824896
            }
        ]
    },
    {
        "quest_description": "Make 3 Nice Throws in a row",
        "quest_reward": "2 Pinap Berry",
        "quest_reward_type": "Item",
        "quest_reward_amount": 2,
        "quest_reward_item_name": "Pinap Berry",
        "quest_reward_pokemon_name": "",
        "quest_reward_pokemon_id": "000",
        "quest_reward_item_id": 705,
        "pokestops": [
            {
                "pokestop_id": "6a2a765de64e487888e7fa496b2618d1.16",
                "name": "Antigo Marco de Correios",
                "latitude": 39.739681,
                "longitude": -8.805175
            }
        ]
    },
    {
        "quest_description": "Make 3 Great Throws",
        "quest_reward": "Clamperl",
        "quest_reward_type": "Pokemon",
        "quest_reward_amount": 1,
        "quest_reward_item_name": "Pokemon",
        "quest_reward_pokemon_name": "Clamperl",
        "quest_reward_pokemon_id": 366,
        "quest_reward_item_id": 0,
        "pokestops": [
            {
                "pokestop_id": "78fe7d9b4b7e3e5c8e7fd8086110becb.16",
                "name": "Azinheira",
                "latitude": 39.747237,
                "longitude": -8.80158
            },
            {
                "pokestop_id": "b64fd16751ac44d7a62ab96a2e39cccc.16",
                "name": "Abra\u00e7o ao Universo",
                "latitude": 39.751515,
                "longitude": -8.814163
            }
        ]
    },
    {
        "quest_description": "Make 5 Nice Throws",
        "quest_reward": "Diglett",
        "quest_reward_type": "Pokemon",
        "quest_reward_amount": 1,
        "quest_reward_item_name": "Pokemon",
        "quest_reward_pokemon_name": "Diglett",
        "quest_reward_pokemon_id": 50,
        "quest_reward_item_id": 0,
        "pokestops": [
            {
                "pokestop_id": "80fff49f00003aadbf32302a836e98ba.16",
                "name": "Rota Arquitect\u00f3nica - Edif\u00edcio Barros Santa Rita",
                "latitude": 39.742059,
                "longitude": -8.808031
            }
        ]
    },
    {
        "quest_description": "Make 3 Great Throws in a row",
        "quest_reward": "5 Ultra Ball",
        "quest_reward_type": "Item",
        "quest_reward_amount": 5,
        "quest_reward_item_name": "Ultra Ball",
        "quest_reward_pokemon_name": "",
        "quest_reward_pokemon_id": "000",
        "quest_reward_item_id": 3,
        "pokestops": [
            {
                "pokestop_id": "89c6d7e56a043bb286e68785a6de9473.16",
                "name": "Galerias S\u00e3o Jos\u00e9",
                "latitude": 39.739852,
                "longitude": -8.808011
            }
        ]
    },
    {
        "quest_description": "Make 5 Curveball Throws in a row",
        "quest_reward": "500 Stardust",
        "quest_reward_type": "Stardust",
        "quest_reward_amount": 500,
        "quest_reward_item_name": "Stardust",
        "quest_reward_pokemon_name": "",
        "quest_reward_pokemon_id": "000",
        "quest_reward_item_id": 0,
        "pokestops": [
            {
                "pokestop_id": "8ca13adcfb603c7f9cf74e600801aa07.16",
                "name": "Mural \"Na Dist\u00e2ncia\"",
                "latitude": 39.736711,
                "longitude": -8.793678
            },
            {
                "pokestop_id": "8cbd770c2c204e229947f1fad6509bd4.16",
                "name": "O intelectual.",
                "latitude": 39.747676,
                "longitude": -8.813754
            }
        ]
    },
    {
        "quest_description": "Make 3 Great Throws",
        "quest_reward": "Kabuto",
        "quest_reward_type": "Pokemon",
        "quest_reward_amount": 1,
        "quest_reward_item_name": "Pokemon",
        "quest_reward_pokemon_name": "Kabuto",
        "quest_reward_pokemon_id": 140,
        "quest_reward_item_id": 0,
        "pokestops": [
            {
                "pokestop_id": "a55789a0b055357b8f42ccdc0907d810.16",
                "name": "Parque Infantil Este",
                "latitude": 39.735664,
                "longitude": -8.800658
            },
            {
                "pokestop_id": "cc4126081db6350b858d7ea581abefdf.16",
                "name": "Faces Cubistas",
                "latitude": 39.750855,
                "longitude": -8.806714
            }
        ]
    },
    {
        "quest_description": "Make 3 Great Curveball Throws",
        "quest_reward": "9 Razz Berry",
        "quest_reward_type": "Item",
        "quest_reward_amount": 9,
        "quest_reward_item_name": "Razz Berry",
        "quest_reward_pokemon_name": "",
        "quest_reward_pokemon_id": "000",
        "quest_reward_item_id": 701,
        "pokestops": [
            {
                "pokestop_id": "a7894b04684c402baea2ab2ec344b50f.16",
                "name": "Jogo da Macaca",
                "latitude": 39.738327,
                "longitude": -8.81087
            }
        ]
    },
    {
        "quest_description": "Make 3 Great Throws in a row",
        "quest_reward": "1 Rare Candy",
        "quest_reward_type": "Item",
        "quest_reward_amount": 1,
        "quest_reward_item_name": "Rare Candy",
        "quest_reward_pokemon_name": "",
        "quest_reward_pokemon_id": "000",
        "quest_reward_item_id": 1301,
        "pokestops": [
            {
                "pokestop_id": "b34bf50d2d6c33b0a1c60bf1526d1854.16",
                "name": "Zona de Merendas e Lazer",
                "latitude": 39.742779,
                "longitude": -8.796153
            }
        ]
    },
    {
        "quest_description": "Make 2 Excellent Throws",
        "quest_reward": "Bagon",
        "quest_reward_type": "Pokemon",
        "quest_reward_amount": 1,
        "quest_reward_item_name": "Pokemon",
        "quest_reward_pokemon_name": "Bagon",
        "quest_reward_pokemon_id": 371,
        "quest_reward_item_id": 0,
        "pokestops": [
            {
                "pokestop_id": "bbc92efd9d1241c8b25bcfdfd74be4e8.11",
                "name": "Est\u00e1tua Lu\u00eds de Cam\u00f5es",
                "latitude": 39.744778,
                "longitude": -8.80632
            },
            {
                "pokestop_id": "d4f83005fb733d4286dc584464d6232a.16",
                "name": "Campo de Basquetebol",
                "latitude": 39.729503,
                "longitude": -8.806066
            }
        ]
    },
    {
        "quest_description": "Make 10 Nice Throws",
        "quest_reward": "Nidoran\u2642",
        "quest_reward_type": "Pokemon",
        "quest_reward_amount": 1,
        "quest_reward_item_name": "Pokemon",
        "quest_reward_pokemon_name": "Nidoran\u2642",
        "quest_reward_pokemon_id": 32,
        "quest_reward_item_id": 0,
        "pokestops": [
            {
                "pokestop_id": "e4f6ae5d813f4e46af63c7039bdeb9ff.16",
                "name": "Clube Acad\u00e9mico Leiria",
                "latitude": 39.738592,
                "longitude": -8.80671
            }
        ]
    }
]